adk_sim_server/__init__.py
adk_sim_server/broadcaster.py
adk_sim_server/cli.py
adk_sim_server/logging.py
adk_sim_server/main.py
adk_sim_server/queue.py
adk_sim_server/session_manager.py
adk_sim_server/settings.py
adk_sim_server/web.py
adk_sim_server/persistence/__init__.py
adk_sim_server/persistence/core.py
adk_sim_server/persistence/database.py
adk_sim_server/persistence/event_repo.py
adk_sim_server/persistence/schema.py
adk_sim_server/persistence/session_repo.py
adk_sim_server/services/__init__.py
adk_sim_server/services/simulator_service.py
adk_sim_server/static/.gitkeep
adk_sim_server/static/3rdpartylicenses.txt
adk_sim_server/static/prerendered-routes.json
adk_sim_server/static/browser/chunk-2DTQDKXS.js
adk_sim_server/static/browser/chunk-3YHSMWVU.js
adk_sim_server/static/browser/chunk-CRN6KGBZ.js
adk_sim_server/static/browser/chunk-I3WCFQUS.js
adk_sim_server/static/browser/chunk-IZQ5VDHL.js
adk_sim_server/static/browser/chunk-PB33TLUV.js
adk_sim_server/static/browser/favicon.ico
adk_sim_server/static/browser/index.html
adk_sim_server/static/browser/main-DDR4HYP7.js
adk_sim_server/static/browser/styles-UZ7DD3YP.css
adk_sim_server/static/browser/media/material-icons-JLIDJUWE.woff
adk_sim_server/static/browser/media/material-icons-LEZCGFVT.woff2
adk_sim_server/static/browser/media/material-icons-outlined-7BWLPMFK.woff2
adk_sim_server/static/browser/media/material-icons-outlined-PCUTWIDZ.woff
adk_sim_server/static/browser/media/material-icons-round-SLOHZIXU.woff
adk_sim_server/static/browser/media/material-icons-round-WEHMTW23.woff2
adk_sim_server/static/browser/media/material-icons-sharp-HCCYMPXE.woff2
adk_sim_server/static/browser/media/material-icons-sharp-U4OLFP3G.woff
adk_sim_server/static/browser/media/material-icons-two-tone-LCGWGE2N.woff
adk_sim_server/static/browser/media/material-icons-two-tone-M5N5K6F5.woff2
adk_sim_server/static/browser/media/roboto-cyrillic-300-normal-5FCNOL5I.woff2
adk_sim_server-0.1.22.dist-info/METADATA
adk_sim_server-0.1.22.dist-info/WHEEL
adk_sim_server-0.1.22.dist-info/entry_points.txt
adk_sim_server-0.1.22.dist-info/RECORD
