Metadata-Version: 2.4
Name: adk-sim-server
Version: 0.1.22
Summary: ADK Agent Simulator - gRPC Server
Requires-Python: >=3.14
Requires-Dist: adk-sim-protos==0.1.22
Requires-Dist: broadcaster>=0.3.1
Requires-Dist: databases[aiosqlite]>=0.9.0
Requires-Dist: grpclib>=0.4.7
Requires-Dist: pydantic-settings>=2.12.0
Requires-Dist: pydantic>=2.10.0
Requires-Dist: python-dotenv>=1.0.1
Requires-Dist: sqlalchemy>=2.0.0
Requires-Dist: starlette>=0.45.0
Requires-Dist: structlog>=25.5.0
Requires-Dist: tenacity>=9.1.2
Requires-Dist: typer>=0.15.0
Requires-Dist: uvicorn>=0.34.0
